intake_sql/__init__.py
intake_sql/_version.py
intake_sql/intake_sql.py
intake_sql/sql_cat.py
intake_sql-0.4.0.dist-info/LICENSE
intake_sql-0.4.0.dist-info/METADATA
intake_sql-0.4.0.dist-info/WHEEL
intake_sql-0.4.0.dist-info/entry_points.txt
intake_sql-0.4.0.dist-info/top_level.txt
intake_sql-0.4.0.dist-info/RECORD
