Metadata-Version: 2.1
Name: intake-sql
Version: 0.4.0
Summary: SQL plugin for Intake
Home-page: https://github.com/ContinuumIO/intake-sql
Maintainer: Martin Durant
Maintainer-email: mdurant@anaconda.com
License: BSD
License-File: LICENSE
Requires-Dist: intake
Requires-Dist: pandas
Requires-Dist: sqlalchemy (>2)
